{
  "employeeNumber": 315035,
  "username": "B038210",
  "firstName": "FirstName315035",
  "middleName": "MiddleName315035",
  "lastName": "LastName315035",
  "fullName": "LastName315035, FirstName315035 MiddleName315035",
  "preferredFirstName": "PrefFirstName315035",
  "preferredLastName": "PrefLastName315035",
  "preferredName": "PrefLastName315035, PrefFirstName315035",
  "gender": "Male",
  "userPersonType": "Employee",
  "systemPersonType": "EMP",
  "workerType": "Regular",
  "employmentCategory": "full-time",
  "isExempt": true,
  "gradeRateStructure": "12 Exempt",
  "emailAddress": "FirstName315035.LastName315035@bestbuy.com",
  "payType": "1",
  "payGroup": "Biweekly_2",
  "employeeStatus": "Active",
  "isActive": true,
  "isTerminated": false,
  "location": {
    "locationId": 900010,
    "locationName": "Corporate 1 MN 900010",
    "primaryLocationPhone": "+  6122911000"
  },
  "jobCode": 48976,
  "jobTitle": "Architect Senior Principal",
  "businessTitle": "Architect Senior Principal",
  "hireDate": "2005-02-24",
  "originalHireDate": "2005-02-24",
  "glLocationOrganizationName": "Corp 1",
  "organizationName": "Digital, Analytics, and Technology",
  "companyName": "Best Buy Technology Services LLC",
  "companyId": 126,
  "costCenter": "Technology Architecture",
  "costCenterId": 957423,
  "glLocationId": "GL_900010",
  "glLocationCodeSubType": "Corporate",
  "glCodeHierarchyKey": "0000",
  "homeAddress": {
    "addressLine1": "831 HEINEL DR",
    "city": "ROSEVILLE",
    "state": "MN",
    "postalCode": "55113-2124",
    "countryCode": "US",
    "county": "RAMSEY"
  },
  "workAddress": {
    "addressLine1": "7601 Penn Avenue South",
    "city": "Richfield",
    "state": "MN",
    "postalCode": "55423-8500",
    "countryCode": "US",
    "county": "Hennepin"
  },
  "workCellPhoneNumber": "+1 (612) 9918598",
  "manager": {
    "employeeNumber": 1388776,
    "username": "A1388776",
    "preferredFirstName": "ManagerFirstName315035",
    "preferredLastName": "ManagerLastName315035",
    "preferredName": "ManagerLastName315035, ManagerFirstName315035",
    "jobCode": 47986,
    "jobTitle": "Distinguished Architect",
    "locationPhone": "+  6122911000"
  },
  "discountEligible": true,
  "workdayId": "00f917a4cb4b1001cd6dbb7c99ea0002",
  "hrPartner": "Shannon Smith (77503)",
  "managementLevel": "5-Director",
  "basePayCurrency": "USD",
  "approvalAuthorityLimit": "250000",
  "isPeopleLeader": "No",
  "anniversaryDate": "2005-02-24-08:00",
  "absence": {
    "ptoBalance": "72",
    "eligibleToPurchasePto": "Eligible",
    "ptoRefreshDate": "2024-02-24-08:00",
    "timeOffPlanType": "PTO (Plan 1)",
    "vacationBalance": "1.92",
    "purchasedPtoBalance": "0",
    "sickPlanEligibility": "Not Eligible",
    "sickPlanBalance": "0",
    "sickBank": "0",
    "sickMandate": "0"
  },
  "createdTimestamp": "2022-05-04T15:19:51.830Z",
  "lastUpdatedTimestamp": "2023-11-06T18:24:23.932Z",
  "modifiedTimestamp": "2023-11-07T10:12:10.137Z"
}